phippery/__init__.py
phippery/cli.py
phippery/eigen.py
phippery/escprof.py
phippery/gampois.py
phippery/modeling.py
phippery/normalize.py
phippery/string.py
phippery/utils.py
phippery/zscore.py
phippery-1.3.1.dist-info/LICENSE
phippery-1.3.1.dist-info/METADATA
phippery-1.3.1.dist-info/WHEEL
phippery-1.3.1.dist-info/entry_points.txt
phippery-1.3.1.dist-info/top_level.txt
phippery-1.3.1.dist-info/RECORD
