Metadata-Version: 2.1
Name: phippery
Version: 1.3.1
Summary: Tools for analyzing PhIP-Seq Data.
Author-email: Jared Galloway <jgallowa@fredhutch.org>, Kevin Sung <ksung@fredhutch.org>
Project-URL: documentation, https://matsengrp.github.io/phippery/
Project-URL: repository, https://github.com/matsengrp/phippery
Keywords: phippery,phipseq,phage,modeling,phip
Classifier: License :: OSI Approved :: GNU Affero General Public License v3
Classifier: Programming Language :: Python
Classifier: Programming Language :: Python :: 3
Requires-Python: >=3.7
License-File: LICENSE
Requires-Dist: click
Requires-Dist: numpy
Requires-Dist: pandas
Requires-Dist: scipy>=1.7.1
Requires-Dist: xarray>=0.19.0
Requires-Dist: statsmodels
Requires-Dist: POT
Requires-Dist: biopython
Provides-Extra: dev
Requires-Dist: setuptools>=58.0; extra == "dev"
Requires-Dist: packaging>=21.0; extra == "dev"
Requires-Dist: pytest; extra == "dev"
Requires-Dist: pytest-pep8; extra == "dev"
Requires-Dist: pytest-datadir; extra == "dev"
Requires-Dist: pre-commit; extra == "dev"
Requires-Dist: black; extra == "dev"
Requires-Dist: sphinx; extra == "dev"
Requires-Dist: sphinx-rtd-theme; extra == "dev"
Requires-Dist: sphinx-click; extra == "dev"
Requires-Dist: bumpver; extra == "dev"
